sphinx_mekki/__init__.py
sphinx_mekki/_static/mekki_handle_download.js
sphinx_mekki/themes/mekki/layout.html
sphinx_mekki/themes/mekki/localtoc.html
sphinx_mekki/themes/mekki/theme.conf
sphinx_mekki/themes/mekki/static/mekki.css_t
sphinx_mekki-0.8.9.dist-info/METADATA
sphinx_mekki-0.8.9.dist-info/WHEEL
sphinx_mekki-0.8.9.dist-info/entry_points.txt
sphinx_mekki-0.8.9.dist-info/licenses/LICENSE
sphinx_mekki-0.8.9.dist-info/RECORD
