Metadata-Version: 2.4
Name: sphinx-mekki
Version: 0.8.9
Summary: A Sphinx extension to embed images, download files, CSSs, and JSs into a single HTML file.
Project-URL: Homepage, https://github.com/wakinotani/sphinx-mekki
Project-URL: Issues, https://github.com/wakinotani/sphinx-mekki/issues
Author-email: Yoshiyuki Wakinotani <wakinotani@gmail.com>
License-File: LICENSE
Classifier: Development Status :: 5 - Production/Stable
Classifier: Environment :: Web Environment
Classifier: Framework :: Sphinx
Classifier: Framework :: Sphinx :: Extension
Classifier: Framework :: Sphinx :: Theme
Classifier: Intended Audience :: Developers
Classifier: License :: OSI Approved :: MIT License
Classifier: Operating System :: OS Independent
Classifier: Programming Language :: Python :: 3
Classifier: Programming Language :: Python :: 3.8
Classifier: Programming Language :: Python :: 3.9
Classifier: Programming Language :: Python :: 3.10
Classifier: Programming Language :: Python :: 3.11
Classifier: Programming Language :: Python :: 3.12
Classifier: Topic :: Documentation :: Sphinx
Classifier: Topic :: Software Development :: Documentation
Classifier: Topic :: Text Processing :: Markup :: HTML
Requires-Python: >=3.8
Requires-Dist: cssutils
Requires-Dist: rjsmin
